{
	"name": "Create Dataverse Raw View",
	"properties": {
		"activities": [
			{
				"name": "Create Pipelines",
				"type": "ExecutePipeline",
				"dependsOn": [],
				"userProperties": [],
				"typeProperties": {
					"pipeline": {
						"referenceName": "2 For Each Table",
						"type": "PipelineReference"
					},
					"waitOnCompletion": true,
					"parameters": {
						"SourceFolderPath": {
							"value": "@pipeline().parameters.SourceFolderPath",
							"type": "Expression"
						},
						"DatabaseName": {
							"value": "@pipeline().parameters.DatabaseName",
							"type": "Expression"
						},
						"StorageAccountContainerName": {
							"value": "@pipeline().parameters.StorageContainerName",
							"type": "Expression"
						},
						"ServerName": {
							"value": "@pipeline().parameters.ServerName",
							"type": "Expression"
						},
						"SchemaName": {
							"value": "@pipeline().parameters.RawView_SchemaName",
							"type": "Expression"
						}
					}
				}
			}
		],
		"parameters": {
			"SourceFolderPath": {
				"type": "string",
				"defaultValue": "DataverseTest"
			},
			"DatabaseName": {
				"type": "string",
				"defaultValue": "wsentsynserverlessdb001"
			},
			"StorageContainerName": {
				"type": "string",
				"defaultValue": "staging"
			},
			"ServerName": {
				"type": "string",
				"defaultValue": "ws-ent-syn-dmp-dev-004-ondemand.sql.azuresynapse.net"
			},
			"RawView_SchemaName": {
				"type": "string",
				"defaultValue": "dbo"
			}
		},
		"folder": {
			"name": "wsentsynserverlessdb001"
		},
		"annotations": []
	}
}